{
    "id":  "doll",
    "name":  "Doll",
    "animations":  {
                       "idle":  {
                                    "label":  "Idle",
                                    "framePattern":  "../../assets/characters/doll-idle/doll-idle-{frame}.webp",
                                    "frameCount":  113,
                                    "framePad":  3,
                                    "frameIntervalMs":  33,
                                    "scale":  1.18,
                                    "offsetXPercent":  0,
                                    "offsetYPercent":  0,
                                    "sideOffsets":  {
                                                        "p1":  {
                                                                   "offsetXPercent":  -8,
                                                                   "fighterOffsetX":  -15,
                                                                   "fighterOffsetY":  -6
                                                               },
                                                        "p2":  {
                                                                   "offsetXPercent":  8,
                                                                   "fighterOffsetX":  15,
                                                                   "fighterOffsetY":  -6
                                                               }
                                                    }
                                },
                       "getUp":  {
                                     "label":  "Get Up",
                                     "framePattern":  "../../assets/characters/doll-get-up/doll-get-up-{frame}.webp",
                                     "frameCount":  169,
                                     "framePad":  3,
                                     "frameIntervalMs":  16,
                                     "scale":  1.2,
                                     "offsetXPercent":  0,
                                     "offsetYPercent":  0,
                                     "sideOffsets":  {
                                                         "p1":  {
                                                                    "offsetXPercent":  -8
                                                                },
                                                         "p2":  {
                                                                    "offsetXPercent":  8
                                                                }
                                                     }
                                 },
                       "crouch":  {
                                      "label":  "Crouch",
                                      "framePattern":  "../../assets/characters/doll-crouch/doll-crouch-{frame}.webp",
                                      "frameCount":  356,
                                      "framePad":  3,
                                      "frameIntervalMs":  8,
                                      "scale":  1.18,
                                      "offsetXPercent":  0,
                                      "offsetYPercent":  0,
                                      "sideOffsets":  {
                                                          "p1":  {
                                                                     "offsetXPercent":  -8
                                                                 },
                                                          "p2":  {
                                                                     "offsetXPercent":  8
                                                                 }
                                                      }
                                  },
                       "jump":  {
                                    "label":  "Jump",
                                    "framePattern":  "../../assets/characters/doll-jump/doll-jump-{frame}.webp",
                                    "frameCount":  113,
                                    "framePad":  3,
                                    "frameIntervalMs":  18,
                                    "scale":  1.18,
                                    "offsetXPercent":  0,
                                    "offsetYPercent":  0,
                                    "sideOffsets":  {
                                                        "p1":  {
                                                                   "offsetXPercent":  -8
                                                               },
                                                        "p2":  {
                                                                   "offsetXPercent":  8
                                                               }
                                                    }
                                },
                       "special":  {
                                       "label":  "Special",
                                       "framePattern":  "../../assets/characters/doll-special/doll-special-{frame}.webp",
                                       "frameCount":  176,
                                       "framePad":  3,
                                       "frameIntervalMs":  12,
                                       "scale":  2.64,
                                       "offsetXPercent":  0,
                                       "offsetYPercent":  0,
                                       "sideOffsets":  {
                                                           "p1":  {
                                                                      "offsetXPercent":  2,
                                                                      "offsetYPercent":  -1,
                                                                      "fighterOffsetX":  108,
                                                                      "fighterOffsetY":  45,
                                                                      "fighterScale":  1
                                                                  },
                                                           "p2":  {
                                                                      "offsetXPercent":  -2,
                                                                      "offsetYPercent":  -1,
                                                                      "fighterOffsetX":  -108,
                                                                      "fighterOffsetY":  45,
                                                                      "fighterScale":  1
                                                                  }
                                                       }
                                   },
                       "ultimate":  {
                                        "label":  "Ultimate",
                                        "framePattern":  "../../assets/characters/doll-ultimate/doll-ultimate-{frame}.webp",
                                        "frameCount":  126,
                                        "framePad":  3,
                                        "frameIntervalMs":  33,
                                        "firstFrameHoldMs":  450
                                    }
                   }
}
